penman/__about__.py
penman/__init__.py
penman/__main__.py
penman/_format.py
penman/_lexer.py
penman/_parse.py
penman/codec.py
penman/constant.py
penman/epigraph.py
penman/exceptions.py
penman/graph.py
penman/interface.py
penman/layout.py
penman/model.py
penman/surface.py
penman/transform.py
penman/tree.py
penman/types.py
penman/models/__init__.py
penman/models/amr.py
penman/models/noop.py
penman-1.3.0.dist-info/METADATA
penman-1.3.0.dist-info/WHEEL
penman-1.3.0.dist-info/entry_points.txt
penman-1.3.0.dist-info/licenses/LICENSE
penman-1.3.0.dist-info/RECORD
