Metadata-Version: 2.1
Name: Penman
Version: 1.3.0
Summary: PENMAN notation for graphs (e.g., AMR)
Project-URL: Homepage, https://github.com/goodmami/penman
Project-URL: Documentation, https://penman.readthedocs.io/
Project-URL: Changelog, https://github.com/goodmami/penman/blob/main/CHANGELOG.md
Project-URL: Source, https://github.com/goodmami/penman
Author-email: Michael Wayne Goodman <goodman.m.w@gmail.com>
License-Expression: MIT
License-File: LICENSE
Keywords: amr,nlp,semantics
Classifier: Development Status :: 4 - Beta
Classifier: Environment :: Console
Classifier: Intended Audience :: Developers
Classifier: Intended Audience :: Information Technology
Classifier: Intended Audience :: Science/Research
Classifier: License :: OSI Approved :: MIT License
Classifier: Programming Language :: Python :: 3
Classifier: Programming Language :: Python :: 3.8
Classifier: Programming Language :: Python :: 3.9
Classifier: Programming Language :: Python :: 3.10
Classifier: Programming Language :: Python :: 3.11
Classifier: Programming Language :: Python :: 3.12
Classifier: Topic :: Scientific/Engineering :: Information Analysis
Classifier: Topic :: Software Development :: Libraries :: Python Modules
Classifier: Topic :: Text Processing :: Linguistic
Classifier: Topic :: Utilities
Requires-Python: >=3.8
